paperbnf.py
paperbnf_lex.py
paperbnf_parser.py
paperbnf-1.0.dist-info/LICENSE
paperbnf-1.0.dist-info/METADATA
paperbnf-1.0.dist-info/WHEEL
paperbnf-1.0.dist-info/top_level.txt
paperbnf-1.0.dist-info/RECORD
