Metadata-Version: 2.1
Name: paperbnf
Version: 1.0
Summary: UNKNOWN
Home-page: https://github.com/thautwarm/paperbnf
Author: thautwarm
Author-email: twshere@outlook.com
License: mit
Keywords: LaTex,BNF
Platform: any
Classifier: Programming Language :: Python :: 3.7
Classifier: Programming Language :: Python :: 3.8
Classifier: Programming Language :: Python :: Implementation :: CPython
Requires-Python: >=3.7.0
